{
	"1": {
		"n": "Shrine to Evara",
		"gn": "Evara the Abundant, Goddess of Plenty",
		"gsn": "Evara the Abundant",
		"gtn": "Evara",
		"d": "Temples built honoring Evara the Abundant will grant an alliance the following bonuses, up to the value of 50%:<br> - Senator travel speed<br> - Senator claim per siege wave<br> - Senator enlistment speed<br> - Charisma regeneration per hour",
		"img": "/images/regional/evarashrine.png",
		"dimg": "/images/city/buildings/icons/eva128.png",
		"limg": "evaralv",
		"simg": "evara32",
		"tooltip": "evaratt",
		"class": "temeva",
		"start": 1052,
		"cl": "evarashrinepic",
		"faith": {
			"1": 1,
			"2": 2,
			"3": 3,
			"4": 4,
			"5": 6,
			"6": 8,
			"7": 10,
			"8": 13,
			"9": 16,
			"10": 20
		},
		"sn": {
			"1": 10000000,
			"2": 30000000,
			"3": 60000000,
			"4": 100000000,
			"5": 250000000,
			"6": 350000000,
			"7": 500000000,
			"8": 800000000,
			"9": 1000000000,
			"10": 1500000000
		},
		"tn": {
			"1": 10000000,
			"2": 40000000,
			"3": 100000000,
			"4": 200000000,
			"5": 450000000,
			"6": 800000000,
			"7": 1300000000,
			"8": 2100000000,
			"9": 3100000000,
			"10": 4600000000
		}
	},
	"2": {
		"n": "Shrine to Vexemis",
		"gn": "Vexemis the Angry, God of War",
		"gsn": "Vexemis the Angry",
		"gtn": "Vexemis",
		"d": "Temples built honoring Vexemis the Angry will grant an alliance the following bonuses, up to the value of 50%:<br> - Vanquisher, Sorcerer, Scout, Horseman and Druid combat value ",
		"img": "/images/regional/vexemisshrine.png",
		"dimg": "/images/city/buildings/icons/vex128.png",
		"limg": "vexlv",
		"simg": "vexemis32",
		"tooltip": "vextt",
		"class": "temvex",
		"start": 1142,
		"cl": "vexemisshrinepic",
		"tn": {
			"1": 10000000,
			"2": 40000000,
			"3": 100000000,
			"4": 200000000,
			"5": 450000000,
			"6": 800000000,
			"7": 1300000000,
			"8": 2100000000,
			"9": 3100000000,
			"10": 4600000000
		},
		"faith": {
			"1": 1,
			"2": 2,
			"3": 3,
			"4": 4,
			"5": 6,
			"6": 8,
			"7": 10,
			"8": 13,
			"9": 16,
			"10": 20
		},
		"sn": {
			"1": 10000000,
			"2": 30000000,
			"3": 60000000,
			"4": 100000000,
			"5": 250000000,
			"6": 350000000,
			"7": 500000000,
			"8": 800000000,
			"9": 1000000000,
			"10": 1500000000
		}
	},
	"3": {
		"n": "Shrine to Domdis",
		"gn": "Domdis the Sturdy, God of the Builders",
		"gsn": "Domdis the Sturdy",
		"gtn": "Domdis",
		"d": "Temples built honoring Domdis the Sturdy will grant an alliance the following bonuses, up to the value of 50<br> - Increased durability of Fortifications and City Buildings<br> - Increased Artillery and Ship travel speeds",
		"img": "/images/regional/domdisshrine.png",
		"dimg": "/images/city/buildings/icons/dom128.png",
		"limg": "domdislv",
		"simg": "domdis32",
		"tooltip": "domdistt",
		"class": "temdom",
		"start": 1232,
		"cl": "domdisshrinepic",
		"sn": {
			"1": 10000000,
			"2": 30000000,
			"3": 60000000,
			"4": 100000000,
			"5": 250000000,
			"6": 350000000,
			"7": 500000000,
			"8": 800000000,
			"9": 1000000000,
			"10": 1500000000
		},
		"faith": {
			"1": 1,
			"2": 2,
			"3": 3,
			"4": 4,
			"5": 6,
			"6": 8,
			"7": 10,
			"8": 13,
			"9": 16,
			"10": 20
		},
		"tn": {
			"1": 10000000,
			"2": 40000000,
			"3": 100000000,
			"4": 200000000,
			"5": 450000000,
			"6": 800000000,
			"7": 1300000000,
			"8": 2100000000,
			"9": 3100000000,
			"10": 4600000000
		}
	},
	"4": {
		"n": "Shrine to Cyndros",
		"gn": "Cyndros the Mighty, God of Strength",
		"gsn": "Cyndros the Mighty",
		"gtn": "Cyndros",
		"d": "Temples built honoring Cyndros the Mighty will grant an alliance the following bonuses, up to the value of 50%:<br> - Increased Battering Ram, Scorpion, and Warship combat values",
		"img": "/images/regional/cyndrosshrine.png",
		"dimg": "/images/city/buildings/icons/cyn128.png",
		"limg": "cyndroslv",
		"simg": "cyndros32",
		"tooltip": "cyndrostt",
		"class": "temcyn",
		"start": 1322,
		"cl": "cyndrosshrinepic",
		"tn": {
			"1": 10000000,
			"2": 40000000,
			"3": 100000000,
			"4": 200000000,
			"5": 450000000,
			"6": 800000000,
			"7": 1300000000,
			"8": 2100000000,
			"9": 3100000000,
			"10": 4600000000
		},
		"faith": {
			"1": 1,
			"2": 2,
			"3": 3,
			"4": 4,
			"5": 6,
			"6": 8,
			"7": 10,
			"8": 13,
			"9": 16,
			"10": 20
		},
		"sn": {
			"1": 10000000,
			"2": 30000000,
			"3": 60000000,
			"4": 100000000,
			"5": 250000000,
			"6": 350000000,
			"7": 500000000,
			"8": 800000000,
			"9": 1000000000,
			"10": 1500000000
		}
	},
	"5": {
		"n": "Shrine to Merius",
		"gn": "Merius the Wealthy, God of Bargaining",
		"gsn": "Merius the Wealthy",
		"gtn": "Merius",
		"d": "Temples built honoring Merius the Wealthy will grant an alliance the following bonuses, up to the value of 50%:<br> - Travel speed of carts and trader ships<br> - Stinger, Galley, and Warship enlistment speeds",
		"img": "/images/regional/meriusshrine.png",
		"dimg": "/images/city/buildings/icons/mer128.png",
		"limg": "meriuslv",
		"simg": "merius32",
		"tooltip": "meriustt",
		"class": "temmer",
		"start": 1412,
		"cl": "meriusshrinepic",
		"faith": {
			"1": 1,
			"2": 2,
			"3": 3,
			"4": 4,
			"5": 6,
			"6": 8,
			"7": 10,
			"8": 13,
			"9": 16,
			"10": 20
		},
		"sn": {
			"1": 10000000,
			"2": 30000000,
			"3": 60000000,
			"4": 100000000,
			"5": 250000000,
			"6": 350000000,
			"7": 500000000,
			"8": 800000000,
			"9": 1000000000,
			"10": 1500000000
		},
		"tn": {
			"1": 10000000,
			"2": 40000000,
			"3": 100000000,
			"4": 200000000,
			"5": 450000000,
			"6": 800000000,
			"7": 1300000000,
			"8": 2100000000,
			"9": 3100000000,
			"10": 4600000000
		}
	},
	"6": {
		"n": "Shrine to Ylanna",
		"gn": "Ylanna the Bawdy, Goddess of the Sea",
		"gsn": "Ylanna the Bawdy",
		"gtn": "Ylanna",
		"d": "Temples built honoring Ylanna the Bawdy a will grant an alliance the following bonuses, up to the value of 50%:<br> - Guards, Ballista, Stinger and Galley combat values",
		"img": "/images/regional/ylannashrine.png",
		"dimg": "/images/city/buildings/icons/yla128.png",
		"limg": "ylannalv",
		"simg": "ylanna32",
		"tooltip": "ylannatt",
		"class": "temyla",
		"start": 1502,
		"cl": "ylannashrinepic",
		"tn": {
			"1": 10000000,
			"2": 40000000,
			"3": 100000000,
			"4": 200000000,
			"5": 450000000,
			"6": 800000000,
			"7": 1300000000,
			"8": 2100000000,
			"9": 3100000000,
			"10": 4600000000
		},
		"sn": {
			"1": 10000000,
			"2": 30000000,
			"3": 60000000,
			"4": 100000000,
			"5": 250000000,
			"6": 350000000,
			"7": 500000000,
			"8": 800000000,
			"9": 1000000000,
			"10": 1500000000
		},
		"faith": {
			"1": 1,
			"2": 2,
			"3": 3,
			"4": 4,
			"5": 6,
			"6": 8,
			"7": 10,
			"8": 13,
			"9": 16,
			"10": 20
		}
	},
	"7": {
		"n": "Shrine to Ibria",
		"gn": "Ibria the Stealthy, Goddess of the Hunt",
		"gsn": "Ibria the Stealthy",
		"gtn": "Ibria",
		"d": "Temples built honoring Ibria the Stealthy will grant an alliance the following bonuses, up to the value of 50%:<br> - Infantry, Scout, and Cavalry travel speeds<br> - Base construction speed in all cities",
		"img": "/images/regional/ibriashrine.png",
		"dimg": "/images/city/buildings/icons/ibr128.png",
		"limg": "ibrialv",
		"simg": "ibria32",
		"tooltip": "ibriatt",
		"class": "temibr",
		"start": 1592,
		"cl": "ibriashrinepic",
		"sn": {
			"1": 10000000,
			"2": 30000000,
			"3": 60000000,
			"4": 100000000,
			"5": 250000000,
			"6": 350000000,
			"7": 500000000,
			"8": 800000000,
			"9": 1000000000,
			"10": 1500000000
		},
		"faith": {
			"1": 1,
			"2": 2,
			"3": 3,
			"4": 4,
			"5": 6,
			"6": 8,
			"7": 10,
			"8": 13,
			"9": 16,
			"10": 20
		},
		"tn": {
			"1": 10000000,
			"2": 40000000,
			"3": 100000000,
			"4": 200000000,
			"5": 450000000,
			"6": 800000000,
			"7": 1300000000,
			"8": 2100000000,
			"9": 3100000000,
			"10": 4600000000
		}
	},
	"8": {
		"n": "Shrine to Naera",
		"gn": "Naera the Stonehearted, Goddess of the Dead",
		"gsn": "Naera the Stonehearted",
		"gtn": "Naera",
		"d": "Temples built honoring Naera the Stonehearted will grant an alliance the following bonuses, up to the value of 50%:<br> - Ranger, Priestess, Triari, Arbalists, and Praetor combat values",
		"img": "/images/regional/naerashrine.png",
		"dimg": "/images/city/buildings/icons/nae128.png",
		"limg": "naeralv",
		"simg": "naera32",
		"tooltip": "naeratt",
		"class": "temnae",
		"start": 1682,
		"cl": "naerashrinepic",
		"sn": {
			"1": 10000000,
			"2": 30000000,
			"3": 60000000,
			"4": 100000000,
			"5": 250000000,
			"6": 350000000,
			"7": 500000000,
			"8": 800000000,
			"9": 1000000000,
			"10": 1500000000
		},
		"faith": {
			"1": 1,
			"2": 2,
			"3": 3,
			"4": 4,
			"5": 6,
			"6": 8,
			"7": 10,
			"8": 13,
			"9": 16,
			"10": 20
		},
		"tn": {
			"1": 10000000,
			"2": 40000000,
			"3": 100000000,
			"4": 200000000,
			"5": 450000000,
			"6": 800000000,
			"7": 1300000000,
			"8": 2100000000,
			"9": 3100000000,
			"10": 4600000000
		}
	}
}